trident/__init__.py
trident/context.py
trident/readable_errors.py
trident/backend/__init__.py
trident/backend/common.py
trident/backend/decorators.py
trident/backend/distribution.py
trident/backend/dtype.py
trident/backend/function.py
trident/backend/graph_tools.py
trident/backend/iteration_tools.py
trident/backend/jax_backend.py
trident/backend/jax_ops.py
trident/backend/jax_serialization.py
trident/backend/load_backend.py
trident/backend/model.py
trident/backend/numpy_ops.py
trident/backend/opencv_backend.py
trident/backend/pillow_backend.py
trident/backend/pytorch_backend.py
trident/backend/pytorch_ops.py
trident/backend/sanitize.py
trident/backend/tensorflow_backend.py
trident/backend/tensorflow_ops.py
trident/backend/tensorflow_serialization.py
trident/backend/tensorspec.py
trident/callbacks/__init__.py
trident/callbacks/callback_base.py
trident/callbacks/dataflow_callbacks.py
trident/callbacks/lr_schedulers.py
trident/callbacks/regularization_callbacks.py
trident/callbacks/saving_strategies.py
trident/callbacks/visualization_callbacks.py
trident/data/__init__.py
trident/data/augment_policy.py
trident/data/bbox.py
trident/data/bbox_common.py
trident/data/char_freq.txt
trident/data/data_loaders.py
trident/data/data_provider.py
trident/data/dataset.py
trident/data/image_common.py
trident/data/image_reader.py
trident/data/label_common.py
trident/data/mask_common.py
trident/data/preprocess_policy.py
trident/data/samplers.py
trident/data/t2s.txt
trident/data/text2pronounce.txt
trident/data/text_common.py
trident/data/text_transforms.py
trident/data/transform.py
trident/data/utils.py
trident/data/vision_transforms.py
trident/layers/__init__.py
trident/layers/jax_activations.py
trident/layers/jax_layers.py
trident/layers/pytorch_activations.py
trident/layers/pytorch_blocks.py
trident/layers/pytorch_initializers.py
trident/layers/pytorch_layers.py
trident/layers/pytorch_normalizations.py
trident/layers/pytorch_pooling.py
trident/layers/pytorch_rnn.py
tridentx-0.7.9.dist-info/LICENSE
tridentx-0.7.9.dist-info/METADATA
tridentx-0.7.9.dist-info/WHEEL
tridentx-0.7.9.dist-info/top_level.txt
tridentx-0.7.9.dist-info/RECORD
