Metadata-Version: 2.1
Name: tridentx
Version: 0.7.9
Summary: Make pytorch and tensorflow two become one.
Download-URL: https://test.pypi.org/project/tridentx
Author: Allan Yiin
Author-email: allanyiin.ai@gmail.com
License: MIT
Keywords: deep learning,machine learning,pytorch,tensorflow,AI
Classifier: Development Status :: 4 - Beta
Classifier: Intended Audience :: Developers
Classifier: Intended Audience :: Education
Classifier: Intended Audience :: Science/Research
Classifier: License :: OSI Approved :: MIT License
Classifier: Programming Language :: Python :: 3.5
Classifier: Programming Language :: Python :: 3.6
Classifier: Programming Language :: Python :: 3.7
Classifier: Programming Language :: Python :: 3.8
Classifier: Programming Language :: Python :: 3.9
Classifier: Topic :: Software Development :: Libraries
Classifier: Topic :: Software Development :: Libraries :: Python Modules
Requires-Python: >=3.5
License-File: LICENSE
Requires-Dist: numpy>=1.18
Requires-Dist: opencv-python
Requires-Dist: six>=1.13.0
Requires-Dist: scikit-image>=0.19.0
Requires-Dist: scipy
Requires-Dist: beautifulsoup4
Requires-Dist: scikit-learn
Requires-Dist: matplotlib>=3.0.2
Requires-Dist: ipython>=7.10.2
Requires-Dist: pillow>=4.1.1
Requires-Dist: setuptools>=42.0.1
Requires-Dist: onnx>=1.4.1
Requires-Dist: tensorboard>=1.15.0
Requires-Dist: dill>=0.3.1
Requires-Dist: tqdm
Requires-Dist: requests
Requires-Dist: h5py
Provides-Extra: tests
Requires-Dist: pytest; extra == "tests"
Requires-Dist: pytest-pep8; extra == "tests"
Requires-Dist: pytest-xdist; extra == "tests"
Requires-Dist: flaky; extra == "tests"
Requires-Dist: pytest-cov; extra == "tests"
Requires-Dist: requests; extra == "tests"
Requires-Dist: markdown; extra == "tests"
Provides-Extra: visualize
Requires-Dist: pydot>=1.2.4; extra == "visualize"
